{
  "tmdb_id": 11023,
  "imdb_id": "tt0328538",
  "title": "Thirteen",
  "year": "2003",
  "genres": [
    "Drama"
  ],
  "runtime": 100,
  "director": "Catherine Hardwicke",
  "cast": [
    "Evan Rachel Wood",
    "Nikki Reed",
    "Holly Hunter",
    "Brady Corbet",
    "Jeremy Sisto"
  ],
  "plot": "When average 13-year-old Tracy befriends Evie, the most popular girl in school, Tracy's world is turned upside down as Evie introduces her to a world of sex, drugs and cash. But it isn't long before Tracy's new world and attitude finally takes a toll on her, her family, and old friends.",
  "streaming_services": [],
  "imdb_rating": "6.8",
  "metascore": "70",
  "rotten_tomatoes": "81%"
}