{
  "tmdb_id": 715931,
  "imdb_id": "tt12530246",
  "title": "Emancipation",
  "year": "2022",
  "genres": [
    "Drama",
    "War",
    "History"
  ],
  "runtime": 132,
  "director": "Antoine Fuqua",
  "cast": [
    "Will Smith",
    "Ben Foster",
    "Charmaine Bingwa",
    "Gilbert Owuor",
    "Ronnie Gene Blevins"
  ],
  "plot": "Inspired by the gripping true story of a man who would do anything for his family\u2014and for freedom. When Peter, an enslaved man, risks his life to escape and return to his family, he embarks on a perilous journey of love and endurance.",
  "streaming_services": [
    "Apple TV+",
    "Apple TV Plus Amazon Channel"
  ],
  "imdb_rating": "6.3",
  "metascore": "53",
  "rotten_tomatoes": "45%"
}