{
  "tmdb_id": 1147400,
  "imdb_id": "tt29259099",
  "title": "Miraculous World: Paris, Tales of Shadybug and Claw Noir",
  "year": "2023",
  "genres": [
    "Animation",
    "Adventure",
    "Action",
    "Fantasy",
    "Family"
  ],
  "runtime": 48,
  "director": "Thomas Astruc",
  "cast": [
    "Annouck Hautbois",
    "Benjamin Bollen",
    "Marie Nonnenmacher",
    "Thierry Kazazian",
    "Fanny Bloc"
  ],
  "plot": "Miraculous holders from another world appear in Paris. They come from a parallel universe where everything is reversed: the holders of Ladybug and Black Cat Miraculouses, Shadybug and Claw Noir, are the bad guys, and the holder of the Butterfly Miraculous, Hesperia, is a superhero. Ladybug and Cat Noir will have to help Hesperia counter the attacks of their evil doubles and prevent them from seizing the Butterfly's Miraculous. Can our heroes also help Hesperia make Shadybug and Claw Noir better people?",
  "streaming_services": [
    "Disney Plus"
  ],
  "imdb_rating": "8.4",
  "metascore": "N/A",
  "rotten_tomatoes": null
}